reesaber/__init__.py
reesaber/builder.py
reesaber/config.py
reesaber/utils.py
reesaber/models/__init__.py
reesaber/models/base.py
reesaber/models/control.py
reesaber/models/driver.py
reesaber/modules/__init__.py
reesaber/modules/base.py
reesaber/modules/blur_saber.py
reesaber/modules/simple_trail.py
reesaber/modules/vanilla_saber.py
reesaber-1.0.1.dist-info/licenses/LICENSE
reesaber-1.0.1.dist-info/METADATA
reesaber-1.0.1.dist-info/WHEEL
reesaber-1.0.1.dist-info/top_level.txt
reesaber-1.0.1.dist-info/RECORD
